{
    
    "costTable": [
    {
        "id": "E2_V3", 
        "regions": [
            {
                "id": "europe-north", 
                "type" : "number", 
                "value": "0.233"
            },
            {
                "id": "europe-west", 
                "type" : "number", 
                "value": "0.252"
            }, 
            {
                "id": "france-central", 
                "type" : "number", 
                "value": "0.248"
            },
            {
                "id": "germany-west-central", 
                "type" : "number", 
                "value": "0.272"
            }, 
            {
                "id": "switzerland-north", 
                "type" : "number", 
                "value": "0.284"
            },
            {
                "id": "united-kingdom-south", 
                "type" : "number", 
                "value": "0.248"
            },
            {
                "id": "united-kingdom-west", 
                "type" : "number", 
                "value": "0.248"
            }
        ]
    }, 
    {
        "id": "AZURE_FUNCTIONS", 
        "regions" : [
            {
                "id": "europe-north", 
                "type" : "number", 
                "value": "0.03583"
            },
            {
                "id": "europe-west", 
                "type" : "number", 
                "value": "0.03583"
            }, 
            {
                "id": "france-central", 
                "type" : "number", 
                "value": "0.03583"
            },
            {
                "id": "germany-west-central", 
                "type" : "number", 
                "value": "0.03583"
            }, 
            {
                "id": "switzerland-north", 
                "type" : "number", 
                "value": "0.03583"
            },
            {
                "id": "united-kingdom-south", 
                "type" : "number", 
                "value": "0.03583"
            },
            {
                "id": "united-kingdom-west", 
                "type" : "number", 
                "value": "0.03583"
            }
        ]
    },
    {
    "id": "AZUREMYSQL",
    "regions": [
        {
            "id": "europe-north", 
            "type" : "number", 
            "value": "0.1033"
        },
        {
            "id": "europe-west", 
            "type" : "number", 
            "value": "0.112652"
        }, 
        {
            "id": "france-central", 
            "type" : "number", 
            "value": "0.1172"
        }
    ]
} 
]
}